urldna/__init__.py
urldna/exceptions/__init__.py
urldna/exceptions/api_exception.py
urldna/models/__init__.py
urldna/models/certificate.py
urldna/models/console_message.py
urldna/models/cookie.py
urldna/models/fast_check.py
urldna/models/favicon.py
urldna/models/http_transaction.py
urldna/models/ip_address.py
urldna/models/malicious.py
urldna/models/page.py
urldna/models/scan.py
urldna/models/scan_feedback.py
urldna/models/scan_result.py
urldna/models/scan_whois.py
urldna/models/screenshot.py
urldna/models/search_result.py
urldna/models/technology.py
urldna/models/user_agent.py
urldna/models/viewport.py
urldna/schemas/__init__.py
urldna/schemas/certificate_schema.py
urldna/schemas/console_message_schema.py
urldna/schemas/cookie_schema.py
urldna/schemas/fast_check_schema.py
urldna/schemas/favicon_schema.py
urldna/schemas/http_transaction_schema.py
urldna/schemas/ip_address_schema.py
urldna/schemas/malicious_schema.py
urldna/schemas/page_schema.py
urldna/schemas/scan_feedback_schema.py
urldna/schemas/scan_result_schema.py
urldna/schemas/scan_schema.py
urldna/schemas/scan_whois_schema.py
urldna/schemas/screenshot_schema.py
urldna/schemas/technology_schema.py
urldna/schemas/user_agent_schema.py
urldna/schemas/viewport_schema.py
urldna-0.0.14.dist-info/LICENSE
urldna-0.0.14.dist-info/METADATA
urldna-0.0.14.dist-info/WHEEL
urldna-0.0.14.dist-info/top_level.txt
urldna-0.0.14.dist-info/RECORD
