Metadata-Version: 2.1
Name: urlDNA
Version: 0.0.14
Summary: The DNA test for websites.
Home-page: https://urldna.io
Author: urlDNA
Author-email: urldna@urldna.io
License: MIT
Keywords: web scraping,website analysis,url scan
Classifier: Programming Language :: Python :: 3
Classifier: License :: OSI Approved :: MIT License
Classifier: Operating System :: OS Independent
License-File: LICENSE
Requires-Dist: requests
Requires-Dist: marshmallow
